[{"train": ["FIS_067_01", "FIS_103_01", "FIS_043_01", "REHEM_03_01", "FIS_059_01", "FIS_110_01", "REHEM_104_01", "FIS_118_01", "REHEM_41_01", "FIS_078_01", "FIS_031_01", "FIS_072_01", "FIS_044_01", "FIS_068_01", "FIS_096_01", "FIS_122_01", "REHEM_106_01", "REHEM_120_01", "REHEM_105_01", "REHEM_118_01", "FIS_005_01", "REHEM_37_01", "REHEM_13_01", "FIS_071_01", "FIS_013_01", "FIS_094_01", "REHEM_35_01", "REHEM_60_01", "FIS_113_01", "REHEM_99_01", "REHEM_121_01", "REHEM_23_01", "FIS_007_01", "REHEM_20_01", "REHEM_22_01", "FIS_095_01", "REHEM_82_01", "FIS_033_01", "FIS_001_01", "FIS_104_01", "REHEM_75_01", "REHEM_70_01", "REHEM_21_01", "REHEM_58_01", "REHEM_36_01", "REHEM_16_01", "FIS_017_01", "REHEM_108_01", "REHEM_34_01", "REHEM_18_01", "FIS_021_01", "REHEM_39_01", "FIS_055_01", "FIS_124_01", "FIS_105_01", "REHEM_55_01", "FIS_116_01", "REHEM_68_01", "REHEM_86_01", "FIS_032_01", "FIS_102_01", "REHEM_111_01", "FIS_046_01", "FIS_025_01"], "val": ["REHEM_102_01", "FIS_037_01", "FIS_117_01", "REHEM_110_01", "FIS_014_01", "REHEM_113_01", "REHEM_63_01", "REHEM_80_01", "REHEM_40_01", "REHEM_08_01", "FIS_088_01", "REHEM_59_01", "FIS_128_01", "FIS_098_01", "REHEM_15_01", "REHEM_88_01", "FIS_084_01"]}, {"train": ["REHEM_102_01", "FIS_037_01", "FIS_117_01", "REHEM_110_01", "FIS_103_01", "FIS_014_01", "REHEM_113_01", "REHEM_63_01", "REHEM_80_01", "FIS_043_01", "REHEM_40_01", "REHEM_08_01", "FIS_088_01", "REHEM_59_01", "FIS_128_01", "FIS_098_01", "REHEM_15_01", "REHEM_88_01", "FIS_084_01", "FIS_031_01", "FIS_096_01", "REHEM_106_01", "REHEM_120_01", "REHEM_105_01", "REHEM_118_01", "REHEM_37_01", "REHEM_13_01", "FIS_071_01", "FIS_013_01", "REHEM_35_01", "FIS_113_01", "REHEM_99_01", "REHEM_23_01", "FIS_007_01", "REHEM_20_01", "REHEM_22_01", "FIS_095_01", "REHEM_82_01", "FIS_033_01", "FIS_001_01", "FIS_104_01", "REHEM_75_01", "REHEM_70_01", "REHEM_21_01", "REHEM_58_01", "REHEM_36_01", "REHEM_16_01", "FIS_017_01", "REHEM_108_01", "REHEM_34_01", "REHEM_18_01", "FIS_021_01", "REHEM_39_01", "FIS_055_01", "FIS_124_01", "FIS_105_01", "REHEM_55_01", "FIS_116_01", "REHEM_68_01", "REHEM_86_01", "FIS_032_01", "FIS_102_01", "REHEM_111_01", "FIS_046_01", "FIS_025_01"], "val": ["FIS_067_01", "REHEM_03_01", "FIS_059_01", "FIS_110_01", "REHEM_104_01", "FIS_118_01", "REHEM_41_01", "FIS_078_01", "FIS_072_01", "FIS_044_01", "FIS_068_01", "FIS_122_01", "FIS_005_01", "FIS_094_01", "REHEM_60_01", "REHEM_121_01"]}, {"train": ["REHEM_102_01", "FIS_037_01", "FIS_117_01", "FIS_067_01", "REHEM_110_01", "FIS_014_01", "REHEM_113_01", "REHEM_63_01", "REHEM_80_01", "REHEM_40_01", "REHEM_08_01", "FIS_088_01", "REHEM_59_01", "REHEM_03_01", "FIS_059_01", "FIS_128_01", "FIS_110_01", "REHEM_104_01", "FIS_098_01", "FIS_118_01", "REHEM_15_01", "REHEM_41_01", "REHEM_88_01", "FIS_084_01", "FIS_078_01", "FIS_031_01", "FIS_072_01", "FIS_044_01", "FIS_068_01", "FIS_096_01", "FIS_122_01", "FIS_005_01", "FIS_071_01", "FIS_013_01", "FIS_094_01", "REHEM_35_01", "REHEM_60_01", "REHEM_99_01", "REHEM_121_01", "REHEM_23_01", "FIS_007_01", "REHEM_22_01", "REHEM_82_01", "FIS_001_01", "REHEM_75_01", "REHEM_36_01", "REHEM_16_01", "FIS_017_01", "REHEM_108_01", "REHEM_34_01", "REHEM_18_01", "FIS_021_01", "REHEM_39_01", "FIS_055_01", "FIS_124_01", "FIS_105_01", "REHEM_55_01", "FIS_116_01", "REHEM_68_01", "REHEM_86_01", "FIS_032_01", "FIS_102_01", "REHEM_111_01", "FIS_046_01", "FIS_025_01"], "val": ["FIS_103_01", "FIS_043_01", "REHEM_106_01", "REHEM_120_01", "REHEM_105_01", "REHEM_118_01", "REHEM_37_01", "REHEM_13_01", "FIS_113_01", "REHEM_20_01", "FIS_095_01", "FIS_033_01", "FIS_104_01", "REHEM_70_01", "REHEM_21_01", "REHEM_58_01"]}, {"train": ["REHEM_102_01", "FIS_037_01", "FIS_117_01", "FIS_067_01", "REHEM_110_01", "FIS_103_01", "FIS_014_01", "REHEM_113_01", "REHEM_63_01", "REHEM_80_01", "FIS_043_01", "REHEM_40_01", "REHEM_08_01", "FIS_088_01", "REHEM_59_01", "REHEM_03_01", "FIS_059_01", "FIS_128_01", "FIS_110_01", "REHEM_104_01", "FIS_098_01", "FIS_118_01", "REHEM_15_01", "REHEM_41_01", "REHEM_88_01", "FIS_084_01", "FIS_078_01", "FIS_072_01", "FIS_044_01", "FIS_068_01", "FIS_122_01", "REHEM_106_01", "REHEM_120_01", "REHEM_105_01", "REHEM_118_01", "FIS_005_01", "REHEM_37_01", "REHEM_13_01", "FIS_071_01", "FIS_094_01", "REHEM_60_01", "FIS_113_01", "REHEM_121_01", "REHEM_20_01", "FIS_095_01", "FIS_033_01", "FIS_104_01", "REHEM_75_01", "REHEM_70_01", "REHEM_21_01", "REHEM_58_01", "REHEM_16_01", "REHEM_34_01", "REHEM_18_01", "FIS_055_01", "FIS_124_01", "FIS_105_01", "REHEM_55_01", "FIS_116_01", "REHEM_68_01", "REHEM_86_01", "FIS_032_01", "REHEM_111_01", "FIS_046_01", "FIS_025_01"], "val": ["FIS_031_01", "FIS_096_01", "FIS_013_01", "REHEM_35_01", "REHEM_99_01", "REHEM_23_01", "FIS_007_01", "REHEM_22_01", "REHEM_82_01", "FIS_001_01", "REHEM_36_01", "FIS_017_01", "REHEM_108_01", "FIS_021_01", "REHEM_39_01", "FIS_102_01"]}, {"train": ["REHEM_102_01", "FIS_037_01", "FIS_117_01", "FIS_067_01", "REHEM_110_01", "FIS_103_01", "FIS_014_01", "REHEM_113_01", "REHEM_63_01", "REHEM_80_01", "FIS_043_01", "REHEM_40_01", "REHEM_08_01", "FIS_088_01", "REHEM_59_01", "REHEM_03_01", "FIS_059_01", "FIS_128_01", "FIS_110_01", "REHEM_104_01", "FIS_098_01", "FIS_118_01", "REHEM_15_01", "REHEM_41_01", "REHEM_88_01", "FIS_084_01", "FIS_078_01", "FIS_031_01", "FIS_072_01", "FIS_044_01", "FIS_068_01", "FIS_096_01", "FIS_122_01", "REHEM_106_01", "REHEM_120_01", "REHEM_105_01", "REHEM_118_01", "FIS_005_01", "REHEM_37_01", "REHEM_13_01", "FIS_013_01", "FIS_094_01", "REHEM_35_01", "REHEM_60_01", "FIS_113_01", "REHEM_99_01", "REHEM_121_01", "REHEM_23_01", "FIS_007_01", "REHEM_20_01", "REHEM_22_01", "FIS_095_01", "REHEM_82_01", "FIS_033_01", "FIS_001_01", "FIS_104_01", "REHEM_70_01", "REHEM_21_01", "REHEM_58_01", "REHEM_36_01", "FIS_017_01", "REHEM_108_01", "FIS_021_01", "REHEM_39_01", "FIS_102_01"], "val": ["FIS_071_01", "REHEM_75_01", "REHEM_16_01", "REHEM_34_01", "REHEM_18_01", "FIS_055_01", "FIS_124_01", "FIS_105_01", "REHEM_55_01", "FIS_116_01", "REHEM_68_01", "REHEM_86_01", "FIS_032_01", "REHEM_111_01", "FIS_046_01", "FIS_025_01"]}]